RTSAI/__init__.py
RTSAI/config.py
RTSAI/main.py
RTSAI/temp/kg_QALD_9/QALD9_construct.py
RTSAI/temp/kg_countries/countries.py
RTSAI-0.1.5.dist-info/METADATA
RTSAI-0.1.5.dist-info/WHEEL
RTSAI-0.1.5.dist-info/entry_points.txt
RTSAI-0.1.5.dist-info/top_level.txt
RTSAI-0.1.5.dist-info/RECORD
